ics_ipa_interface-1.0.6-py3.7-nspkg.pth
intrepidcs/ipa_interface/__init__.py
intrepidcs/ipa_interface/ipa_interface.py
ics_ipa_interface-1.0.6.dist-info/METADATA
ics_ipa_interface-1.0.6.dist-info/WHEEL
ics_ipa_interface-1.0.6.dist-info/namespace_packages.txt
ics_ipa_interface-1.0.6.dist-info/top_level.txt
ics_ipa_interface-1.0.6.dist-info/RECORD
